bgfactory/__init__.py
bgfactory/common/__init__.py
bgfactory/common/config.py
bgfactory/common/profiler.py
bgfactory/components/__init__.py
bgfactory/components/cairo_helpers.py
bgfactory/components/card_sheet.py
bgfactory/components/component.py
bgfactory/components/constants.py
bgfactory/components/grid.py
bgfactory/components/pango_helpers.py
bgfactory/components/shape.py
bgfactory/components/source.py
bgfactory/components/test text bounds.py
bgfactory/components/test_surface_source.py
bgfactory/components/text.py
bgfactory/components/transformations.py
bgfactory/components/utils.py
bgfactory-0.1.1.dist-info/LICENSE.txt
bgfactory-0.1.1.dist-info/METADATA
bgfactory-0.1.1.dist-info/WHEEL
bgfactory-0.1.1.dist-info/top_level.txt
bgfactory-0.1.1.dist-info/RECORD
