Metadata-Version: 2.1
Name: bgfactory
Version: 0.1.1
Summary: Board Game Factory - a framework for creating and scaling up production of  vector graphics assets, e.g. for board games.
Home-page: https://github.com/avolny/board-game-factory
Author: Adam Volný
Author-email: adam.volny@gmail.com
License: UNKNOWN
Project-URL: Bug Tracker, https://github.com/avolny/board-game-factory/issues
Keywords: board,game,factory,bgf,vector,graphics
Platform: UNKNOWN
Classifier: Development Status :: 3 - Alpha
Classifier: Intended Audience :: Developers
Classifier: Topic :: Multimedia :: Graphics
Classifier: License :: OSI Approved :: MIT License
Classifier: Programming Language :: Python :: 3
Requires-Python: >=3.6
License-File: LICENSE.txt
Requires-Dist: cairocffi
Requires-Dist: pangocffi
Requires-Dist: pillow
